src/ucla_geotech_tools/auto_fchp/__init__.py
src/ucla_geotech_tools/auto_fchp/auto_fchp_2_0_0.py
ucla_geotech_tools_auto_fchp-2.0.0.dist-info/LICENSE.txt
ucla_geotech_tools_auto_fchp-2.0.0.dist-info/METADATA
ucla_geotech_tools_auto_fchp-2.0.0.dist-info/WHEEL
ucla_geotech_tools_auto_fchp-2.0.0.dist-info/RECORD
