Metadata-Version: 2.1
Name: ucla-geotech-tools.auto-fchp
Version: 2.0.0
Summary: A Python package for selecting a high-pass corner frequency for filtering ground motion records
License: LICENSE.txt
Author: Scott J. Brandenberg
Requires-Python: >=3.8,<4.0
Classifier: License :: Other/Proprietary License
Classifier: Programming Language :: Python :: 3
Classifier: Programming Language :: Python :: 3.8
Classifier: Programming Language :: Python :: 3.9
Classifier: Programming Language :: Python :: 3.10
Classifier: Programming Language :: Python :: 3.11
Classifier: Programming Language :: Python :: 3.12
Requires-Dist: numpy (>=1.22,<2.0)
Requires-Dist: scipy (>=1.8,<2.0)
